photokml.py
photokml-0.1.1.dist-info/LICENSE.txt
photokml-0.1.1.dist-info/METADATA
photokml-0.1.1.dist-info/WHEEL
photokml-0.1.1.dist-info/entry_points.txt
photokml-0.1.1.dist-info/top_level.txt
photokml-0.1.1.dist-info/RECORD
