Metadata-Version: 2.1
Name: photokml
Version: 0.1.1
Summary: Link your photos into a KML ("Google Earth") file based on their geolocation
Home-page: https://github.com/blinkingtwelve/photokml
Author: blinkingtwelve
Author-email: blinkingtwelve@gavagai.eu
License: GPL-3.0+
Project-URL: Documentation, https://github.com/blinkingtwelve/photokml/README.md
Project-URL: Source, https://github.com/blinkingtwelve/photokml
Keywords: GIS kml
Platform: UNKNOWN
Classifier: Development Status :: 4 - Beta
Classifier: Environment :: Console
Classifier: Intended Audience :: End Users/Desktop
Classifier: License :: OSI Approved :: GNU General Public License v3 or later (GPLv3+)
Classifier: Operating System :: OS Independent
Classifier: Topic :: Multimedia :: Graphics :: Presentation
Classifier: Programming Language :: Python :: 3
Requires-Python: >=3.6
License-File: LICENSE.txt
Requires-Dist: simplekml (<1.4.0,>=1.3.1)
Requires-Dist: piexif (<1.2.0,>=1.1.3)
